simple_sso/__init__.py
simple_sso/exceptions.py
simple_sso/models.py
simple_sso/utils.py
simple_sso/sso_client/__init__.py
simple_sso/sso_client/client.py
simple_sso/sso_server/__init__.py
simple_sso/sso_server/apps.py
simple_sso/sso_server/models.py
simple_sso/sso_server/server.py
simple_sso/sso_server/migrations/0001_initial.py
simple_sso/sso_server/migrations/0002_consumer_name_max_length.py
simple_sso/sso_server/migrations/0003_token_redirect_to_max_length.py
simple_sso/sso_server/migrations/__init__.py
tests/__init__.py
tests/settings.py
tests/test_core.py
tests/test_migrations.py
tests/urls.py
tests/utils/__init__.py
tests/utils/context_managers.py
django_simple_sso-1.3.0.dist-info/LICENSE
django_simple_sso-1.3.0.dist-info/METADATA
django_simple_sso-1.3.0.dist-info/WHEEL
django_simple_sso-1.3.0.dist-info/top_level.txt
django_simple_sso-1.3.0.dist-info/RECORD
