Metadata-Version: 2.1
Name: django-simple-sso
Version: 1.3.0
Summary: Simple SSO for Django
Home-page: http://github.com/aldryn/django-simple-sso
Author: Divio AG
Author-email: info@divio.com
License: BSD-3-Clause
Classifier: Development Status :: 5 - Production/Stable
Classifier: Environment :: Web Environment
Classifier: Intended Audience :: Developers
Classifier: License :: OSI Approved :: BSD License
Classifier: Operating System :: OS Independent
Classifier: Programming Language :: Python
Classifier: Programming Language :: Python :: 3
Classifier: Programming Language :: Python :: 3.5
Classifier: Programming Language :: Python :: 3.6
Classifier: Programming Language :: Python :: 3.7
Classifier: Programming Language :: Python :: 3.8
Classifier: Framework :: Django
Classifier: Framework :: Django :: 2.2
Classifier: Framework :: Django :: 3.0
Classifier: Framework :: Django :: 3.1
Classifier: Topic :: Internet :: WWW/HTTP
Classifier: Topic :: Internet :: WWW/HTTP :: Dynamic Content
Classifier: Topic :: Software Development
Classifier: Topic :: Software Development :: Libraries
License-File: LICENSE
Requires-Dist: Django >=2.2
Requires-Dist: itsdangerous <1.0.0
Requires-Dist: requests
